<?xml version="1.0"?>
<!DOCTYPE hibernate-mapping PUBLIC "-//Hibernate/Hibernate Mapping DTD 3.0//EN"
"http://www.hibernate.org/dtd/hibernate-mapping-3.0.dtd">
<!-- Generated Sep 7, 2015 3:42:27 PM by Hibernate Tools 4.3.1 -->
<hibernate-mapping>
    <class name="Hibernate.Artista" table="artista" catalog="estampados" optimistic-lock="version">
        <id name="idArtista" type="java.lang.Integer">
            <column name="idArtista" />
            <generator class="identity" />
        </id>
        <many-to-one name="usuario" class="Hibernate.Usuario" fetch="select">
            <column name="Usuario_idusuario" not-null="true" />
        </many-to-one>
        <property name="createTime" type="timestamp">
            <column name="create_time" length="19" />
        </property>
        <property name="nombre" type="string">
            <column name="nombre" length="45" />
        </property>
        <property name="telefono" type="string">
            <column name="telefono" length="45" />
        </property>
        <property name="direccion" type="string">
            <column name="direccion" length="45" />
        </property>
        <set name="estampados" table="estampado" inverse="true" lazy="false" fetch="select">
            <key>
                <column name="Artista_idArtista" not-null="true" />
            </key>
            <one-to-many class="Hibernate.Estampado" />
        </set>
    </class>
</hibernate-mapping>
